amd_gaia-0.15.2.dist-info/licenses/LICENSE.md
gaia/__init__.py
gaia/cli.py
gaia/logger.py
gaia/perf_analysis.py
gaia/security.py
gaia/util.py
gaia/version.py
gaia/agents/__init__.py
gaia/agents/base/__init__.py
gaia/agents/base/agent.py
gaia/agents/base/api_agent.py
gaia/agents/base/console.py
gaia/agents/base/errors.py
gaia/agents/base/mcp_agent.py
gaia/agents/base/tools.py
gaia/agents/blender/__init__.py
gaia/agents/blender/agent.py
gaia/agents/blender/agent_simple.py
gaia/agents/blender/app.py
gaia/agents/blender/app_simple.py
gaia/agents/blender/core/__init__.py
gaia/agents/blender/core/materials.py
gaia/agents/blender/core/objects.py
gaia/agents/blender/core/rendering.py
gaia/agents/blender/core/scene.py
gaia/agents/blender/core/view.py
gaia/agents/chat/__init__.py
gaia/agents/chat/agent.py
gaia/agents/chat/app.py
gaia/agents/chat/session.py
gaia/agents/chat/tools/__init__.py
gaia/agents/chat/tools/file_tools.py
gaia/agents/chat/tools/rag_tools.py
gaia/agents/chat/tools/shell_tools.py
gaia/agents/code/__init__.py
gaia/agents/code/agent.py
gaia/agents/code/cli.py
gaia/agents/code/models.py
gaia/agents/code/schema_inference.py
gaia/agents/code/system_prompt.py
gaia/agents/code/orchestration/__init__.py
gaia/agents/code/orchestration/checklist_executor.py
gaia/agents/code/orchestration/checklist_generator.py
gaia/agents/code/orchestration/orchestrator.py
gaia/agents/code/orchestration/project_analyzer.py
gaia/agents/code/orchestration/template_catalog.py
gaia/agents/code/orchestration/factories/__init__.py
gaia/agents/code/orchestration/factories/base.py
gaia/agents/code/orchestration/factories/nextjs_factory.py
gaia/agents/code/orchestration/factories/python_factory.py
gaia/agents/code/orchestration/steps/__init__.py
gaia/agents/code/orchestration/steps/base.py
gaia/agents/code/orchestration/steps/error_handler.py
gaia/agents/code/orchestration/steps/nextjs.py
gaia/agents/code/orchestration/steps/python.py
gaia/agents/code/orchestration/workflows/__init__.py
gaia/agents/code/orchestration/workflows/base.py
amd_gaia-0.15.2.dist-info/METADATA
amd_gaia-0.15.2.dist-info/WHEEL
amd_gaia-0.15.2.dist-info/entry_points.txt
amd_gaia-0.15.2.dist-info/top_level.txt
amd_gaia-0.15.2.dist-info/RECORD
