Metadata-Version: 2.4
Name: amd-gaia
Version: 0.15.2
Summary: GAIA is a lightweight agent framework designed for the edge and AI PCs.
Home-page: https://github.com/amd/gaia
Author: AMD
License: MIT
Classifier: Development Status :: 4 - Beta
Classifier: Intended Audience :: Developers
Classifier: License :: OSI Approved :: MIT License
Classifier: Operating System :: OS Independent
Classifier: Programming Language :: Python :: 3
Classifier: Programming Language :: Python :: 3.10
Classifier: Programming Language :: Python :: 3.11
Classifier: Programming Language :: Python :: 3.12
Classifier: Topic :: Scientific/Engineering :: Artificial Intelligence
Requires-Python: >=3.10
License-File: LICENSE.md
Requires-Dist: openai
Requires-Dist: pydantic>=2.9.2
Requires-Dist: transformers
Requires-Dist: accelerate
Requires-Dist: python-dotenv
Requires-Dist: aiohttp
Requires-Dist: rich
Requires-Dist: watchdog>=2.1.0
Requires-Dist: pillow>=9.0.0
Provides-Extra: api
Requires-Dist: fastapi>=0.115.0; extra == "api"
Requires-Dist: uvicorn>=0.32.0; extra == "api"
Requires-Dist: python-multipart>=0.0.9; extra == "api"
Provides-Extra: audio
Requires-Dist: torch<2.4,>=2.0.0; extra == "audio"
Requires-Dist: torchvision<0.19.0; extra == "audio"
Requires-Dist: torchaudio; extra == "audio"
Provides-Extra: blender
Requires-Dist: bpy; extra == "blender"
Provides-Extra: mcp
Requires-Dist: mcp>=1.1.0; extra == "mcp"
Requires-Dist: starlette; extra == "mcp"
Requires-Dist: uvicorn; extra == "mcp"
Provides-Extra: dev
Requires-Dist: pytest; extra == "dev"
Requires-Dist: pytest-benchmark; extra == "dev"
Requires-Dist: pytest-mock; extra == "dev"
Requires-Dist: pytest-asyncio; extra == "dev"
Requires-Dist: memory_profiler; extra == "dev"
Requires-Dist: matplotlib; extra == "dev"
Requires-Dist: adjustText; extra == "dev"
Requires-Dist: plotly; extra == "dev"
Requires-Dist: black; extra == "dev"
Requires-Dist: pylint; extra == "dev"
Requires-Dist: isort; extra == "dev"
Requires-Dist: flake8; extra == "dev"
Requires-Dist: autoflake; extra == "dev"
Requires-Dist: mypy; extra == "dev"
Requires-Dist: bandit; extra == "dev"
Requires-Dist: responses; extra == "dev"
Requires-Dist: requests; extra == "dev"
Provides-Extra: eval
Requires-Dist: anthropic; extra == "eval"
Requires-Dist: bs4; extra == "eval"
Requires-Dist: scikit-learn>=1.5.0; extra == "eval"
Requires-Dist: numpy<2.3.0,>=2.0; extra == "eval"
Requires-Dist: pypdf; extra == "eval"
Provides-Extra: talk
Requires-Dist: pyaudio; extra == "talk"
Requires-Dist: openai-whisper; extra == "talk"
Requires-Dist: numpy==1.26.4; extra == "talk"
Requires-Dist: kokoro>=0.3.1; extra == "talk"
Requires-Dist: soundfile; extra == "talk"
Requires-Dist: sounddevice; extra == "talk"
Provides-Extra: youtube
Requires-Dist: llama-index-readers-youtube-transcript; extra == "youtube"
Provides-Extra: rag
Requires-Dist: pypdf; extra == "rag"
Requires-Dist: pymupdf>=1.24.0; extra == "rag"
Requires-Dist: sentence-transformers; extra == "rag"
Requires-Dist: faiss-cpu>=1.7.0; extra == "rag"
Provides-Extra: lint
Requires-Dist: black; extra == "lint"
Requires-Dist: pylint; extra == "lint"
Requires-Dist: isort; extra == "lint"
Requires-Dist: flake8; extra == "lint"
Requires-Dist: autoflake; extra == "lint"
Requires-Dist: mypy; extra == "lint"
Requires-Dist: bandit; extra == "lint"
Dynamic: author
Dynamic: classifier
Dynamic: description
Dynamic: description-content-type
Dynamic: home-page
Dynamic: license
Dynamic: license-file
Dynamic: provides-extra
Dynamic: requires-dist
Dynamic: requires-python
Dynamic: summary
